collective.ploneintranet-1.0.0a2-py3.11-nspkg.pth
collective/ploneintranet/__init__.py
collective/ploneintranet/configure.zcml
collective/ploneintranet/dependencies.zcml
collective/ploneintranet/distributions.zcml
collective/ploneintranet/handler.py
collective/ploneintranet/interfaces.py
collective/ploneintranet/profiles.zcml
collective/ploneintranet/testing.py
collective/ploneintranet/distributions/volto/image.png
collective/ploneintranet/distributions/volto/profiles.json
collective/ploneintranet/distributions/volto/schema.json
collective/ploneintranet/distributions/volto/content/content.json
collective/ploneintranet/distributions/volto/content/ordering.json
collective/ploneintranet/distributions/volto/content/portal.json
collective/ploneintranet/distributions/volto/content/blobs/a98774abf06e49078f3f206a8b055dc2-image/plone-foundation-logo.png
collective/ploneintranet/distributions/volto/content/blobs/c98f1f1eceab478097ed7d5ca13e0101-image/image.png
collective/ploneintranet/distributions/volto/content/blobs/f96cfb63b6284c49a49b9dd45e98394b-image/image.png
collective/ploneintranet/locales/__init__.py
collective/ploneintranet/locales/collective.ploneintranet.pot
collective/ploneintranet/locales/update.py
collective/ploneintranet/locales/en/LC_MESSAGES/collective.ploneintranet.po
collective/ploneintranet/profiles/default/browserlayer.xml
collective/ploneintranet/profiles/default/catalog.xml
collective/ploneintranet/profiles/default/metadata.xml
collective/ploneintranet/profiles/default/theme.xml
collective/ploneintranet/profiles/default/types.xml
collective/ploneintranet/profiles/default/userschema.xml
collective/ploneintranet/profiles/default/registry/plone.app.discussion.interfaces.IDiscussionSettings.xml
collective/ploneintranet/profiles/default/registry/plone.base.interfaces.controlpanel.IMailSchema.xml
collective/ploneintranet/profiles/default/registry/plone.base.interfaces.controlpanel.INavigationSchema.xml
collective.ploneintranet-1.0.0a2.dist-info/LICENSE.GPL
collective.ploneintranet-1.0.0a2.dist-info/LICENSE.md
collective.ploneintranet-1.0.0a2.dist-info/METADATA
collective.ploneintranet-1.0.0a2.dist-info/WHEEL
collective.ploneintranet-1.0.0a2.dist-info/entry_points.txt
collective.ploneintranet-1.0.0a2.dist-info/namespace_packages.txt
collective.ploneintranet-1.0.0a2.dist-info/top_level.txt
collective.ploneintranet-1.0.0a2.dist-info/RECORD
